leonapp/__init__.py
leonapp/launcher.py
leonapp-1.0.4.data/data/leonapp_data/332566c2-8f0b-4f1a-a8b3-75e97a0627f2.png
leonapp-1.0.4.data/data/leonapp_data/PKG-INFO
leonapp-1.0.4.data/data/leonapp_data/README-APP.md
leonapp-1.0.4.data/data/leonapp_data/README.md
leonapp-1.0.4.data/data/leonapp_data/__init__.py
leonapp-1.0.4.data/data/leonapp_data/app_detail_window.py
leonapp-1.0.4.data/data/leonapp_data/build.txt
leonapp-1.0.4.data/data/leonapp_data/config.json
leonapp-1.0.4.data/data/leonapp_data/config.py
leonapp-1.0.4.data/data/leonapp_data/fluent_design_example.py
leonapp-1.0.4.data/data/leonapp_data/icon.ico
leonapp-1.0.4.data/data/leonapp_data/icon.jpeg
leonapp-1.0.4.data/data/leonapp_data/launcher.py
leonapp-1.0.4.data/data/leonapp_data/leonapp_gui.log
leonapp-1.0.4.data/data/leonapp_data/leonapp_gui.py
leonapp-1.0.4.data/data/leonapp_data/nuitka-crash-report.xml
leonapp-1.0.4.data/data/leonapp_data/setup.cfg
leonapp-1.0.4.data/data/leonapp_data/落日下载_-_下载B站视频_installer.exe
leonapp-1.0.4.dist-info/METADATA
leonapp-1.0.4.dist-info/WHEEL
leonapp-1.0.4.dist-info/entry_points.txt
leonapp-1.0.4.dist-info/top_level.txt
leonapp-1.0.4.dist-info/RECORD
