Metadata-Version: 2.1
Name: leonapp
Version: 1.0.4
Summary: LeonAPP应用程序启动器
Home-page: https://github.com/JGZYES/leonapp
Author: JGZ_YES
Author-email: luoriguodu@qq.com
Classifier: Programming Language :: Python :: 3
Classifier: License :: OSI Approved :: MIT License
Classifier: Operating System :: OS Independent
Requires-Python: >=3.6
